<?xml version="1.0" encoding="utf-8"?>
<search>
  
  
  
  <entry>
    <title>FastAPI部署到Vercel实现基于Python的无服务器函数</title>
    <link href="/p/49350.html"/>
    <url>/p/49350.html</url>
    
    <content type="html"><![CDATA[<blockquote><p>施工中</p></blockquote>]]></content>
    
    
    <categories>
      
      <category>白嫖万法</category>
      
    </categories>
    
    
    <tags>
      
      <tag>Vercel</tag>
      
      <tag>Python</tag>
      
      <tag>FastAPI</tag>
      
    </tags>
    
  </entry>
  
  
  
  <entry>
    <title>建站之后，应该干什么？(1)</title>
    <link href="/p/33392.html"/>
    <url>/p/33392.html</url>
    
    <content type="html"><![CDATA[<blockquote><p>这篇文章依旧有彩蛋（以后的文章也会有彩蛋）</p></blockquote><p>相信很多新晋站长应在这广袤无垠的互联网世界撑起了自己的小帐篷，但却十分迷茫，我建站完了之后该干啥呢？🤔️</p><p>今天我们就来解决这个问题。</p><h2 id="数据统计"><a href="#数据统计" class="headerlink" title="数据统计"></a>数据统计</h2><p>首先，作为站长，当然要知道自己的网站数据，市面上的数据统计工具有很多，但是有的不易接入，有的难于分析，所以，这里我推荐<a href="https://www.umeng.com/web">友盟+网站统计 | 即安即用，实时统计网站流量数据 (umeng.com)</a>这个东西那可谓是大有来历，它是原来的<strong>CNZZ</strong>，各种功能一应俱全，很多网站都在使用。</p><h3 id="CNZZ"><a href="#CNZZ" class="headerlink" title="CNZZ"></a>CNZZ</h3><h4 id="网站接入"><a href="#网站接入" class="headerlink" title="网站接入"></a>网站接入</h4><p>首先，打开CNZZ的官网<a href="https://www.umeng.com/web">友盟+网站统计 | 即安即用，实时统计网站流量数据 (umeng.com)</a>，点击进入控制台，选择添加站点</p><p>不讲了，具体原因大家自己看：</p><p><img src="https://fastly.jsdelivr.net/gh/Redish101/cdn@src/img/20220315210032.png" alt="友盟官方的公告"></p><h3 id="百度统计"><a href="#百度统计" class="headerlink" title="百度统计"></a>百度统计</h3><p>首先我们打开官网：<a href="https://tongji.baidu.com/">官网</a></p><p>恭喜你，找到了<a href="https://redish101.github.io/jspvz">彩蛋</a></p><p>之后的事情按着教程来就可以了。</p><p>我才不会告诉你我是不想写。</p><h2 id="参考文献"><a href="#参考文献" class="headerlink" title="参考文献"></a>参考文献</h2><ol><li>(2022, February 18). 关于友盟+ U-Web 统计分析产品调整的公告. Info. <a href="https://info.umeng.com/detail?id=550&amp;cateId=1">https://info.umeng.com/detail?id=550&amp;cateId=1</a></li></ol>]]></content>
    
    
    <categories>
      
      <category>教程</category>
      
    </categories>
    
    
    <tags>
      
      <tag>建站</tag>
      
    </tags>
    
  </entry>
  
  
  
  <entry>
    <title>我的Fluid主题配置文件参考</title>
    <link href="/p/39585.html"/>
    <url>/p/39585.html</url>
    
    <content type="html"><![CDATA[<script src="https://gist.github.com/Redish101/06f7befeea0959a7580b7df37d8babbe.js"></script>]]></content>
    
    
    <categories>
      
      <category>Hexo教程</category>
      
    </categories>
    
    
    <tags>
      
      <tag>Hexo</tag>
      
      <tag>Fluid</tag>
      
    </tags>
    
  </entry>
  
  
  
  <entry>
    <title>如何才能把py文件编译为可执行文件？</title>
    <link href="/p/15511.html"/>
    <url>/p/15511.html</url>
    
    <content type="html"><![CDATA[<p>有时候，烦人的甲方会要求我们把py程序编译为可执行文件，这时候要怎么办呢，用<strong>pyinstaller</strong></p><h2 id="安装"><a href="#安装" class="headerlink" title="安装"></a>安装</h2><figure class="highlight bash"><table><tr><td class="gutter"><pre><span class="line">1</span><br></pre></td><td class="code"><pre><code class="hljs bash">pip3 install pyinstaller<br></code></pre></td></tr></table></figure><h2 id="使用"><a href="#使用" class="headerlink" title="使用"></a>使用</h2><figure class="highlight bash"><table><tr><td class="gutter"><pre><span class="line">1</span><br></pre></td><td class="code"><pre><code class="hljs bash">pyinstaller 你的文件.py<br></code></pre></td></tr></table></figure>]]></content>
    
    
    <categories>
      
      <category>Python教程</category>
      
    </categories>
    
    
    <tags>
      
      <tag>pyinstaller</tag>
      
    </tags>
    
  </entry>
  
  
  
  <entry>
    <title>docsify - 一个优雅的静态文档生成器</title>
    <link href="/p/45082.html"/>
    <url>/p/45082.html</url>
    
    <content type="html"><![CDATA[<blockquote><p>我的同学<strong>宋紫睿</strong>为这篇文章作出了不可磨灭的贡献。<br>阅读之前，告诉大家一个消息:<strong>本文有彩蛋</strong>。</p></blockquote><h2 id="docsify好在哪里"><a href="#docsify好在哪里" class="headerlink" title="docsify好在哪里"></a>docsify好在哪里</h2><p>开源项目的文档往往是一个很大的问题，许多静态站点生成器并不能兼顾<strong>强大</strong>与<strong>简单</strong>。</p><span id="more"></span><h3 id="对比"><a href="#对比" class="headerlink" title="对比"></a>对比</h3><h4 id="Sphinx"><a href="#Sphinx" class="headerlink" title="Sphinx"></a>Sphinx</h4><p>先拿Sphinx来说吧，Sphinx因背后有python的驱动，功能十分强大，但是<code>reStructuredText</code>的复杂也劝退了许多人。</p><h4 id="Vuepress"><a href="#Vuepress" class="headerlink" title="Vuepress"></a>Vuepress</h4><p>相比之下，vuepress在文档的编写上就没有那么复杂了，毕竟<code>markdown</code>还是很简单的。<br>But，vuepress的配置实在是太复杂了，而且构建速度及其缓慢，最重要的是需要<code>JavaScript</code>的基础。</p><h4 id="mkdocs"><a href="#mkdocs" class="headerlink" title="mkdocs"></a>mkdocs</h4><p>mkdocs可以说是能和docsify抗衡了，但是，mkdocs需要构建</p><h2 id="使用"><a href="#使用" class="headerlink" title="使用"></a>使用</h2><p>经过上面的的对比，docsify的优点已经很明显了，下面我们就来安装docsify</p><h3 id="安装"><a href="#安装" class="headerlink" title="安装"></a>安装</h3><p>全局安装Docsify-cli:</p><figure class="highlight bash"><table><tr><td class="gutter"><pre><span class="line">1</span><br><span class="line">2</span><br></pre></td><td class="code"><pre><code class="hljs bash">yarn global add docsify-cli<br><span class="hljs-comment"># 或者使用npm</span><br></code></pre></td></tr></table></figure><h3 id="开始一个项目"><a href="#开始一个项目" class="headerlink" title="开始一个项目"></a>开始一个项目</h3><figure class="highlight bash"><table><tr><td class="gutter"><pre><span class="line">1</span><br></pre></td><td class="code"><pre><code class="hljs bash">docsify init &lt;项目路径&gt;<br></code></pre></td></tr></table></figure><h3 id="配置"><a href="#配置" class="headerlink" title="配置"></a>配置</h3><p>配置也很简单，可以参考<a href="https://docsify.js.org/#/zh-cn/configuration">配置项 (docsify.js.org)</a></p><h3 id="写作"><a href="#写作" class="headerlink" title="写作"></a>写作</h3><p>这个更简单，只需要在<code>docs</code>文件夹里新建<code>markdown</code>文件即可。<br>(别说你不会，送你个指南<a href="https://markdown.com.cn/">Markdown 官方教程</a>)</p><h4 id="路径问题"><a href="#路径问题" class="headerlink" title="路径问题"></a>路径问题</h4><p>这里要注意一下路径：</p><p>假设你的目录结构如下：</p><figure class="highlight text"><table><tr><td class="gutter"><pre><span class="line">1</span><br><span class="line">2</span><br><span class="line">3</span><br><span class="line">4</span><br><span class="line">5</span><br><span class="line">6</span><br><span class="line">7</span><br></pre></td><td class="code"><pre><code class="hljs text">.<br>└── docs<br>├── README.md<br>├── guide.md<br>└── zh-cn<br>├── README.md<br>└── guide.md<br></code></pre></td></tr></table></figure><p>那么渲染后的路径就是：</p><figure class="highlight text"><table><tr><td class="gutter"><pre><span class="line">1</span><br><span class="line">2</span><br><span class="line">3</span><br><span class="line">4</span><br></pre></td><td class="code"><pre><code class="hljs text">docs/README.md        =&gt; http://domain.com<br>docs/guide.md         =&gt; http://domain.com/guide<br>docs/zh-cn/README.md  =&gt; http://domain.com/zh-cn/<br>docs/zh-cn/guide.md   =&gt; http://domain.com/zh-cn/guide<br></code></pre></td></tr></table></figure><h2 id="部署"><a href="#部署" class="headerlink" title="部署"></a>部署</h2><h3 id="Github-Pages"><a href="#Github-Pages" class="headerlink" title="Github Pages"></a>Github Pages</h3><p>将Github Pages的工作目录设置到docsify所在目录。</p><h3 id="Vercel"><a href="#Vercel" class="headerlink" title="Vercel"></a>Vercel</h3><p>选中docsify所在仓库，点击下面的deploy</p><h3 id="其他"><a href="#其他" class="headerlink" title="其他"></a>其他</h3><p>具体我也不会用，只需要记住两点：</p><ul><li>无需构建</li><li>工作目录在根目录</li></ul><h2 id="参考文献"><a href="#参考文献" class="headerlink" title="参考文献"></a>参考文献</h2><ol><li><a href="https://docsify.js.org/#/zh-cn/">docsify中文文档</a></li><li><a href="https://vercel.com/docs">Introduction to Vercel – Vercel Docs</a></li><li><a href="https://segmentfault.com/a/1190000040063325?utm_source=tag-newest">Vercel 上自动部署你的个人博客 Hugo - SegmentFault 思否</a></li></ol><p>感谢阅读<br>彩蛋：🥚呵呵呵，答应你们的蛋。</p>]]></content>
    
    
    <categories>
      
      <category>教程</category>
      
    </categories>
    
    
    <tags>
      
      <tag>docsify</tag>
      
      <tag>静态站点</tag>
      
    </tags>
    
  </entry>
  
  
  
  <entry>
    <title>你好Hexo</title>
    <link href="/p/8071.html"/>
    <url>/p/8071.html</url>
    
    <content type="html"><![CDATA[<p>啊啊啊啊啊，我终于升级完了，和wp的臃肿相比，Hexo显得十分简洁。<br>大家都说hexo写作困难，那是在没有HexoPlusPlus的情况下，部署后，写作体验比Typecho还要nice。  </p><figure class="highlight python"><table><tr><td class="gutter"><pre><span class="line">1</span><br></pre></td><td class="code"><pre><code class="hljs python"><span class="hljs-built_in">print</span>(<span class="hljs-string">&quot;Hello world&quot;</span>)<br></code></pre></td></tr></table></figure>]]></content>
    
    
    <categories>
      
      <category>Hexo教程</category>
      
    </categories>
    
    
    <tags>
      
      <tag>Hexo</tag>
      
      <tag>静态博客</tag>
      
    </tags>
    
  </entry>
  
  
  
  
  
  
  <entry>
    <title></title>
    <link href="/"/>
    <url>/</url>
    
    <content type="html"><![CDATA[5a34563731cc11c60e7a525a25620fb2]]></content>
    
  </entry>
  
  
  
  <entry>
    <title>分类</title>
    <link href="/"/>
    <url>/</url>
    
    <content type="html"><![CDATA[]]></content>
    
  </entry>
  
  
  
  <entry>
    <title>Redish101 Blog Friend Links条款与申请方式</title>
    <link href="/"/>
    <url>/</url>
    
    <content type="html"><![CDATA[<h2 id="0-总则"><a href="#0-总则" class="headerlink" title="0.总则"></a>0.总则</h2><p>为了规范化本站友链功能的运营，优化友链的成员项，提高友链成员文章的质量，制定本条款。</p><h2 id="1-要求"><a href="#1-要求" class="headerlink" title="1.要求"></a>1.要求</h2><h3 id="域名"><a href="#域名" class="headerlink" title="域名"></a>域名</h3><p>您的网站必须拥有独立域名（<code>github.io</code>、<code>vercel.app</code>等域名除外），若网站部署在顶级<code>Apex</code>域内或<code>www</code>域内无需验证；若部署在<code>二级域名</code>，则需将域名以<code>TXT</code>方式解析<code>Redish101-friend-links</code>到<code>redish101-friend-links.xxx.xxx</code>，在完成验证后可安全删除DNS记录。  </p><p>国内服务器请尽量提供域名对应的<code>ICP备案号</code>。</p><h3 id="内容"><a href="#内容" class="headerlink" title="内容"></a>内容</h3><p>需要有三篇以上原创文章（不包括广告类文章），并且内容不违反<code>中华人民共和国相关法律</code>。<br>友链部分必须有本站链接，以下为本站信息</p><figure class="highlight yaml"><table><tr><td class="gutter"><pre><span class="line">1</span><br><span class="line">2</span><br><span class="line">3</span><br><span class="line">4</span><br></pre></td><td class="code"><pre><code class="hljs yaml"><span class="hljs-string">标题:</span> <span class="hljs-string">Redish101</span> <span class="hljs-string">Blog</span><br><span class="hljs-string">介绍:</span> <span class="hljs-string">Redish101的小站</span><br><span class="hljs-attr">logo:</span> <span class="hljs-string">https://blog.redish101.top/favicon.ico</span><br><span class="hljs-string">链接:</span> <span class="hljs-string">https://blog.redish101.top/</span><br></code></pre></td></tr></table></figure><h2 id="2-申请"><a href="#2-申请" class="headerlink" title="2.申请"></a>2.申请</h2><p>Fork本站的<a href="https://github.com/redish101/blog">源代码仓库</a>，在<code>fluid.config.yml</code>文件中的第<code>916行</code>中<code>links</code>项中的<code>items</code>列表末尾添加内容，以下为格式demo:</p><figure class="highlight yaml"><table><tr><td class="gutter"><pre><span class="line">1</span><br><span class="line">2</span><br><span class="line">3</span><br><span class="line">4</span><br><span class="line">5</span><br><span class="line">6</span><br></pre></td><td class="code"><pre><code class="hljs yaml"><span class="hljs-bullet">-</span> &#123;<br>        <span class="hljs-attr">title:</span> <span class="hljs-string">&#x27;站点标题&#x27;</span>,<br>        <span class="hljs-attr">intro:</span> <span class="hljs-string">&#x27;站点简介&#x27;</span>,<br>        <span class="hljs-attr">link:</span> <span class="hljs-string">&#x27;站点链接&#x27;</span>,<br>        <span class="hljs-attr">avatar:</span> <span class="hljs-string">&#x27;站点logo（或博主头像）&#x27;</span><br>    &#125;<br></code></pre></td></tr></table></figure><p>将<code>package.json</code>中的<code>version</code>项中的第三位加一，如<code>0.0.9</code>需改为<code>0.0.10</code>。<br>将<code>themes/fluid/source/sw.js</code>中第<code>47行</code>中版本号改为上一步中指定的版本号。</p><blockquote><p>为什么这样做？<br>本站使用npm cdn优选实现加速效果，每次更新都需要指定版本号以保证内容的正常加载</p></blockquote><p>在仓库中提交PR，等待审核。  </p><h2 id="3-申请后"><a href="#3-申请后" class="headerlink" title="3.申请后"></a>3.申请后</h2><p>审核通过后我们会通过您网站的留言板，评论区等方式通知您 ，请留意站点评论区&#x2F;留言板。<br>请尽量保证您网站的运行正常，如停止运行，请联系我们。</p><h2 id="4-总结"><a href="#4-总结" class="headerlink" title="4.总结"></a>4.总结</h2><p>感谢您的配合，通过后，请您保证网站内容的更新，谢谢。</p><p>Redish101<br>最后修订于2022年5月10日</p>]]></content>
    
  </entry>
  
  
  
  <entry>
    <title>友情链接</title>
    <link href="/"/>
    <url>/</url>
    
    <content type="html"><![CDATA[]]></content>
    
  </entry>
  
  
  
  <entry>
    <title>Redish101的电台</title>
    <link href="/"/>
    <url>/</url>
    
    <content type="html"><![CDATA[    <div id="aplayer-EXlDtrRu" class="aplayer aplayer-tag-marker meting-tag-marker"         data-id="7319831612" data-server="netease" data-type="playlist" data-mode="circulation" data-autoplay="false" data-mutex="true" data-listmaxheight="340px" data-preload="auto" data-theme="#3F51B5"    ></div>]]></content>
    
  </entry>
  
  
  
  <entry>
    <title>标签</title>
    <link href="/"/>
    <url>/</url>
    
    <content type="html"><![CDATA[]]></content>
    
  </entry>
  
  
  
  <entry>
    <title>说说</title>
    <link href="/"/>
    <url>/</url>
    
    <content type="html"><![CDATA[<!-- 引用 artitalk --><script type="text/javascript" src="https://unpkg.com/artitalk"></script><!-- 存放说说的容器 --><div id="artitalk_main"></div><script>new Artitalk({    appId: 'iV3QLOJANq343CgzyoF8qFzQ-MdYXbMMI', // Your LeanCloud appId    appKey: 'fPaPSnidXEj8XPMakfm0GlfU',    color1: '#9bcd9b',    color2: '#9bcd9b'})</script>]]></content>
    
  </entry>
  
  
  
</search>
